hermes/typeo/__init__.py
hermes/typeo/actions.py
hermes/typeo/typeo.py
hermes.typeo-0.1.5.dist-info/WHEEL
hermes.typeo-0.1.5.dist-info/METADATA
hermes.typeo-0.1.5.dist-info/RECORD
