Metadata-Version: 2.1
Name: hermes.typeo
Version: 0.1.5
Summary: Utilities for running functions as scripts
Author: Alec Gunny
Author-email: alec.gunny@gmail.com
Requires-Python: >=3.8,<4.0
Classifier: Programming Language :: Python :: 3
Classifier: Programming Language :: Python :: 3.8
Classifier: Programming Language :: Python :: 3.9
Classifier: Programming Language :: Python :: 3.10
Requires-Dist: toml (>=0.10.2,<0.11.0)
